{"is_source_file": true, "format": "TypeScript", "description": "Tailwind CSS configuration file specifying content paths and theme extensions for a frontend project.", "external_files": ["tailwindcss"], "external_methods": [], "published": [], "classes": [], "methods": [], "calls": ["satisfies"], "search-terms": ["tailwind", "content", "theme", "extend", "fontFamily", "Config", "tailwind.config.ts"], "state": 2, "file_id": 11, "knowledge_revision": 23, "git_revision": "b48ee87735a91dc5d5161f08ecedd11ed6723e29", "ctags": [], "hash": "ec9c3bff099c7a629e56845efd338c42", "format-version": 4, "code-base-name": "notes_app_frontend", "filename": "notes_app_frontend/tailwind.config.ts", "revision_history": [{"23": "b48ee87735a91dc5d5161f08ecedd11ed6723e29"}]}